jupyter_bridge/__init__.py
jupyter_bridge/_version.py
jupyter_bridge-0.4.0.data/data/share/jupyter/labextensions/jupyter_bridge/build_log.json
jupyter_bridge-0.4.0.data/data/share/jupyter/labextensions/jupyter_bridge/package.json
jupyter_bridge-0.4.0.data/data/share/jupyter/labextensions/jupyter_bridge/static/232c6f6a7678304f9efa.woff2
jupyter_bridge-0.4.0.data/data/share/jupyter/labextensions/jupyter_bridge/static/9174757efc83e072436e.ttf
jupyter_bridge-0.4.0.data/data/share/jupyter/labextensions/jupyter_bridge/static/ae17c16afbea216707b2.woff2
jupyter_bridge-0.4.0.data/data/share/jupyter/labextensions/jupyter_bridge/static/b4990d0d0c5f5d38d62e.ttf
jupyter_bridge-0.4.0.data/data/share/jupyter/labextensions/jupyter_bridge/static/c27da6f833431da5aa29.woff2
jupyter_bridge-0.4.0.data/data/share/jupyter/labextensions/jupyter_bridge/static/c7a869faca299d15be10.woff2
jupyter_bridge-0.4.0.data/data/share/jupyter/labextensions/jupyter_bridge/static/e28096fa75a96ac77020.ttf
jupyter_bridge-0.4.0.data/data/share/jupyter/labextensions/jupyter_bridge/static/ff8f525fb050c5d24519.ttf
jupyter_bridge-0.4.0.data/data/share/jupyter/labextensions/jupyter_bridge/static/lib_index_js.02286465dcbd27fa97e8.js
jupyter_bridge-0.4.0.data/data/share/jupyter/labextensions/jupyter_bridge/static/lib_index_js.02286465dcbd27fa97e8.js.map
jupyter_bridge-0.4.0.data/data/share/jupyter/labextensions/jupyter_bridge/static/lib_index_js.06015f0ce76bc05b7fe8.js
jupyter_bridge-0.4.0.data/data/share/jupyter/labextensions/jupyter_bridge/static/lib_index_js.06015f0ce76bc05b7fe8.js.map
jupyter_bridge-0.4.0.data/data/share/jupyter/labextensions/jupyter_bridge/static/lib_index_js.091c9ea7e7bb83a831c7.js
jupyter_bridge-0.4.0.data/data/share/jupyter/labextensions/jupyter_bridge/static/lib_index_js.091c9ea7e7bb83a831c7.js.map
jupyter_bridge-0.4.0.data/data/share/jupyter/labextensions/jupyter_bridge/static/lib_index_js.0d9df70ca8cce91a53ce.js
jupyter_bridge-0.4.0.dist-info/METADATA
jupyter_bridge-0.4.0.dist-info/WHEEL
jupyter_bridge-0.4.0.dist-info/licenses/LICENSE
jupyter_bridge-0.4.0.dist-info/RECORD
