Metadata-Version: 2.3
Name: jupyter_bridge
Version: 0.4.0
Dynamic: Keywords
Summary: A JupyterLab extension that adds footer buttons to code cells for improved interactivity and visibility control, supporting operations like running cells, hiding/showing code, and managing output directly from the cell interface. Initial functionality included to mark documentation cells that are controlled by their corresponding code cells.
Project-URL: Homepage, https://github.com/LtStarbuck1030/jupyter_bridge
Project-URL: Bug Tracker, https://github.com/LtStarbuck1030/jupyter_bridge/issues
Project-URL: Repository, https://github.com/LtStarbuck1030/jupyter_bridge.git
Author-email: Lisa Marie Meyers <lisamarie9006@gmail.com>
License: BSD 3-Clause License
License-File: LICENSE
Classifier: Framework :: Jupyter
Classifier: Framework :: Jupyter :: JupyterLab
Classifier: Framework :: Jupyter :: JupyterLab :: 4
Classifier: Framework :: Jupyter :: JupyterLab :: Extensions
Classifier: Framework :: Jupyter :: JupyterLab :: Extensions :: Prebuilt
Classifier: License :: OSI Approved :: BSD License
Classifier: Programming Language :: Python
Classifier: Programming Language :: Python :: 3
Classifier: Programming Language :: Python :: 3.8
Classifier: Programming Language :: Python :: 3.9
Classifier: Programming Language :: Python :: 3.10
Classifier: Programming Language :: Python :: 3.11
Classifier: Programming Language :: Python :: 3.12
Requires-Python: >=3.8
